complex.py
complex-0.2.0.dist-info/LICENSE
complex-0.2.0.dist-info/METADATA
complex-0.2.0.dist-info/WHEEL
complex-0.2.0.dist-info/top_level.txt
complex-0.2.0.dist-info/RECORD
